tortoise_filters/__init__.py
tortoise_filters/exceptions.py
tortoise_filters/filter_fields.py
tortoise_filters/filterset.py
tortoise_filters-0.5.dist-info/LICENSE
tortoise_filters-0.5.dist-info/METADATA
tortoise_filters-0.5.dist-info/WHEEL
tortoise_filters-0.5.dist-info/top_level.txt
tortoise_filters-0.5.dist-info/RECORD
