Metadata-Version: 2.1
Name: tortoise-filters
Version: 0.5
Summary: A filtering library with automatical documentation for tortoise orm
Home-page: https://github.com/Brusnen/tortoise-filters
Author: Sergey Brusnov
Author-email: sergey.brusnov1900@gmail.com
License: MIT
License-File: LICENSE
Requires-Dist: tortoise-orm ==0.21.5
Requires-Dist: fastapi ==0.112.0
